dappi/__init__.py
dappi/__main__.py
dappi/all.py
dappi/dates.py
dappi/message.py
dappi/parser.py
dappi/user.py
dappi-1.0.8.dist-info/LICENSE
dappi-1.0.8.dist-info/METADATA
dappi-1.0.8.dist-info/WHEEL
dappi-1.0.8.dist-info/entry_points.txt
dappi-1.0.8.dist-info/top_level.txt
dappi-1.0.8.dist-info/RECORD
