Metadata-Version: 2.1
Name: dappi
Version: 1.0.8
Summary: Parse messages from discord server exports into csv files
Home-page: https://github.com/Andrew-Pynch/dappi
Author: Andrew Pynch
Author-email: andrewpynchbusiness@gmail.com
License: MIT
Platform: UNKNOWN
Classifier: License :: OSI Approved :: MIT License
Classifier: Programming Language :: Python :: 3
Classifier: Programming Language :: Python :: 3.7
Requires-Dist: beautifulsoup4
